odoo/addons/ssi_voucher_refund_settlement/README.rst
odoo/addons/ssi_voucher_refund_settlement/__init__.py
odoo/addons/ssi_voucher_refund_settlement/__manifest__.py
odoo/addons/ssi_voucher_refund_settlement/menu.xml
odoo/addons/ssi_voucher_refund_settlement/data/account_journal_data.xml
odoo/addons/ssi_voucher_refund_settlement/data/account_voucher_type_allowed_journal_data.xml
odoo/addons/ssi_voucher_refund_settlement/data/account_voucher_type_data.xml
odoo/addons/ssi_voucher_refund_settlement/data/approval_template_purchase_refund_settlement_data.xml
odoo/addons/ssi_voucher_refund_settlement/data/approval_template_sale_refund_settlement_data.xml
odoo/addons/ssi_voucher_refund_settlement/data/ir_sequence_data.xml
odoo/addons/ssi_voucher_refund_settlement/data/ir_windows_action_data.xml
odoo/addons/ssi_voucher_refund_settlement/data/policy_template_purchase_refund_settlement_data.xml
odoo/addons/ssi_voucher_refund_settlement/data/policy_template_sale_refund_settlement_data.xml
odoo/addons/ssi_voucher_refund_settlement/data/sequence_template_purchase_settlement_data.xml
odoo/addons/ssi_voucher_refund_settlement/data/sequence_template_sale_settlement_data.xml
odoo/addons/ssi_voucher_refund_settlement/demo/account_journal_demo.xml
odoo/addons/ssi_voucher_refund_settlement/demo/account_voucher_type_allowed_journal_demo.xml
odoo/addons/ssi_voucher_refund_settlement/models/__init__.py
odoo/addons/ssi_voucher_refund_settlement/models/purchase_refund_settlement.py
odoo/addons/ssi_voucher_refund_settlement/models/sale_refund_settlement.py
odoo/addons/ssi_voucher_refund_settlement/security/ir.model.access.csv
odoo/addons/ssi_voucher_refund_settlement/security/ir_module_category_data.xml
odoo/addons/ssi_voucher_refund_settlement/security/ir_rule_data.xml
odoo/addons/ssi_voucher_refund_settlement/security/res_group_data.xml
odoo/addons/ssi_voucher_refund_settlement/static/description/banner.png
odoo/addons/ssi_voucher_refund_settlement/static/description/icon.png
odoo14_addon_ssi_voucher_refund_settlement-14.0.2.3.0.dist-info/METADATA
odoo14_addon_ssi_voucher_refund_settlement-14.0.2.3.0.dist-info/WHEEL
odoo14_addon_ssi_voucher_refund_settlement-14.0.2.3.0.dist-info/top_level.txt
odoo14_addon_ssi_voucher_refund_settlement-14.0.2.3.0.dist-info/RECORD
